pizero_gpslog/DejaVuSansCondensed.ttf
pizero_gpslog/DejaVuSansMono.ttf
pizero_gpslog/__init__.py
pizero_gpslog/converter.py
pizero_gpslog/displaymanager.py
pizero_gpslog/fakeled.py
pizero_gpslog/gpsd.py
pizero_gpslog/installer.py
pizero_gpslog/runner.py
pizero_gpslog/screentest.py
pizero_gpslog/utils.py
pizero_gpslog/version.py
pizero_gpslog/displays/__init__.py
pizero_gpslog/displays/adafruit4567.py
pizero_gpslog/displays/base.py
pizero_gpslog/displays/dummy.py
pizero_gpslog/displays/epd2in13bc.py
pizero_gpslog/extradata/__init__.py
pizero_gpslog/extradata/base.py
pizero_gpslog/extradata/dummy.py
pizero_gpslog/extradata/gq_gmc500plus.py
pizero_gpslog/tests/__init__.py
pizero_gpslog/tests/test_version.py
pizero_gpslog-1.1.0.dist-info/LICENSE
pizero_gpslog-1.1.0.dist-info/METADATA
pizero_gpslog-1.1.0.dist-info/WHEEL
pizero_gpslog-1.1.0.dist-info/entry_points.txt
pizero_gpslog-1.1.0.dist-info/top_level.txt
pizero_gpslog-1.1.0.dist-info/RECORD
