Metadata-Version: 2.1
Name: pizero-gpslog
Version: 1.1.0
Summary: Raspberry Pi Zero gpsd logger with status LEDs.
Home-page: https://github.com/jantman/pizero-gpslog
Author: Jason Antman
Author-email: jason@jasonantman.com
License: UNKNOWN
Keywords: raspberry pi rpi gps log logger gpsd
Platform: UNKNOWN
Classifier: Development Status :: 5 - Production/Stable
Classifier: Environment :: No Input/Output (Daemon)
Classifier: Intended Audience :: End Users/Desktop
Classifier: Natural Language :: English
Classifier: Operating System :: POSIX :: Linux
Classifier: Topic :: Other/Nonlisted Topic
Classifier: Topic :: System :: Logging
Classifier: Topic :: Utilities
Classifier: License :: OSI Approved :: GNU Affero General Public License v3 or later (AGPLv3+)
Classifier: Programming Language :: Python :: 3 :: Only
Classifier: Programming Language :: Python :: 3.7
Classifier: Programming Language :: Python :: 3.8
Requires-Dist: gpiozero
Requires-Dist: gpxpy
Requires-Dist: pint
Requires-Dist: pillow
